{
  "parent": "minecraft:block/thin_block",
  "elements": [
    {
      "faces": {
        "down": {
          "texture": "#texture"
        },
        "east": {
          "texture": "#texture"
        },
        "north": {
          "texture": "#texture"
        },
        "south": {
          "texture": "#texture"
        },
        "up": {
          "texture": "#texture"
        },
        "west": {
          "texture": "#texture"
        }
      },
      "from": [
        0,
        0,
        0
      ],
      "to": [
        16,
        1,
        16
      ]
    }
  ],
  "textures": {
    "texture": "paracosm:block/city_rug_left"
  }
}